Classfile /E:/gmjavadev/devploment/src/test/java/com/quickly/devploment/single/SingleInstance.class
  Last modified 2020-4-3; size 1974 bytes
  MD5 checksum 7ee4a4bf5138af8e5a8bea1637d58150
  Compiled from "SingleInstance.java"
public class com.quickly.devploment.single.SingleInstance
  minor version: 0
  major version: 52
  flags: ACC_PUBLIC, ACC_SUPER
Constant pool:
    #1 = Methodref          #25.#43       // java/lang/Object."<init>":()V
    #2 = Fieldref           #3.#44        // com/quickly/devploment/single/SingleInstance.singleObject:Lcom/quickly/devploment/single/SingleObject;
    #3 = Class              #45           // com/quickly/devploment/single/SingleInstance
    #4 = Class              #46           // com/quickly/devploment/single/SingleObject
    #5 = String             #47           // name
    #6 = String             #48           // port
    #7 = Methodref          #4.#49        // com/quickly/devploment/single/SingleObject."<init>":(Ljava/lang/String;Ljava/lang/String;)V
    #8 = Class              #50           // java/lang/Thread
    #9 = InvokeDynamic      #0:#55        // #0:run:()Ljava/lang/Runnable;
   #10 = Methodref          #8.#56        // java/lang/Thread."<init>":(Ljava/lang/Runnable;)V
   #11 = Methodref          #8.#57        // java/lang/Thread.start:()V
   #12 = Methodref          #3.#58        // com/quickly/devploment/single/SingleInstance.getSingleObject:()Lcom/quickly/devploment/single/SingleObject;
   #13 = Methodref          #4.#59        // com/quickly/devploment/single/SingleObject.getPort:()Ljava/lang/String;
   #14 = Fieldref           #60.#61       // java/lang/System.out:Ljava/io/PrintStream;
   #15 = Class              #62           // java/lang/StringBuilder
   #16 = Methodref          #15.#43       // java/lang/StringBuilder."<init>":()V
   #17 = String             #63           // ThreadName :
   #18 = Methodref          #15.#64       // java/lang/StringBuilder.append:(Ljava/lang/String;)Ljava/lang/StringBuilder;
   #19 = Methodref          #8.#65        // java/lang/Thread.currentThread:()Ljava/lang/Thread;
   #20 = Methodref          #8.#66        // java/lang/Thread.getName:()Ljava/lang/String;
   #21 = String             #67           //  _
   #22 = Methodref          #15.#68       // java/lang/StringBuilder.append:(Ljava/lang/Object;)Ljava/lang/StringBuilder;
   #23 = Methodref          #15.#69       // java/lang/StringBuilder.toString:()Ljava/lang/String;
   #24 = Methodref          #70.#71       // java/io/PrintStream.println:(Ljava/lang/String;)V
   #25 = Class              #72           // java/lang/Object
   #26 = Utf8               singleObject
   #27 = Utf8               Lcom/quickly/devploment/single/SingleObject;
   #28 = Utf8               <init>
   #29 = Utf8               ()V
   #30 = Utf8               Code
   #31 = Utf8               LineNumberTable
   #32 = Utf8               getSingleObject
   #33 = Utf8               ()Lcom/quickly/devploment/single/SingleObject;
   #34 = Utf8               StackMapTable
   #35 = Class              #72           // java/lang/Object
   #36 = Class              #73           // java/lang/Throwable
   #37 = Utf8               main
   #38 = Utf8               ([Ljava/lang/String;)V
   #39 = Utf8               lambda$main$0
   #40 = Class              #46           // com/quickly/devploment/single/SingleObject
   #41 = Utf8               SourceFile
   #42 = Utf8               SingleInstance.java
   #43 = NameAndType        #28:#29       // "<init>":()V
   #44 = NameAndType        #26:#27       // singleObject:Lcom/quickly/devploment/single/SingleObject;
   #45 = Utf8               com/quickly/devploment/single/SingleInstance
   #46 = Utf8               com/quickly/devploment/single/SingleObject
   #47 = Utf8               name
   #48 = Utf8               port
   #49 = NameAndType        #28:#74       // "<init>":(Ljava/lang/String;Ljava/lang/String;)V
   #50 = Utf8               java/lang/Thread
   #51 = Utf8               BootstrapMethods
   #52 = MethodHandle       #6:#75        // invokestatic java/lang/invoke/LambdaMetafactory.metafactory:(Ljava/lang/invoke/MethodHandles$Lookup;Ljava/lang/String;Ljava/lang/invoke/MethodType;Ljava/lang/invoke/MethodType;Ljava/lang/invoke/MethodHandle;Ljava/lang/invoke/MethodType;)Ljava/lang/invoke/CallSite;
   #53 = MethodType         #29           //  ()V
   #54 = MethodHandle       #6:#76        // invokestatic com/quickly/devploment/single/SingleInstance.lambda$main$0:()V
   #55 = NameAndType        #77:#78       // run:()Ljava/lang/Runnable;
   #56 = NameAndType        #28:#79       // "<init>":(Ljava/lang/Runnable;)V
   #57 = NameAndType        #80:#29       // start:()V
   #58 = NameAndType        #32:#33       // getSingleObject:()Lcom/quickly/devploment/single/SingleObject;
   #59 = NameAndType        #81:#82       // getPort:()Ljava/lang/String;
   #60 = Class              #83           // java/lang/System
   #61 = NameAndType        #84:#85       // out:Ljava/io/PrintStream;
   #62 = Utf8               java/lang/StringBuilder
   #63 = Utf8               ThreadName :
   #64 = NameAndType        #86:#87       // append:(Ljava/lang/String;)Ljava/lang/StringBuilder;
   #65 = NameAndType        #88:#89       // currentThread:()Ljava/lang/Thread;
   #66 = NameAndType        #90:#82       // getName:()Ljava/lang/String;
   #67 = Utf8                _
   #68 = NameAndType        #86:#91       // append:(Ljava/lang/Object;)Ljava/lang/StringBuilder;
   #69 = NameAndType        #92:#82       // toString:()Ljava/lang/String;
   #70 = Class              #93           // java/io/PrintStream
   #71 = NameAndType        #94:#95       // println:(Ljava/lang/String;)V
   #72 = Utf8               java/lang/Object
   #73 = Utf8               java/lang/Throwable
   #74 = Utf8               (Ljava/lang/String;Ljava/lang/String;)V
   #75 = Methodref          #96.#97       // java/lang/invoke/LambdaMetafactory.metafactory:(Ljava/lang/invoke/MethodHandles$Lookup;Ljava/lang/String;Ljava/lang/invoke/MethodType;Ljava/lang/invoke/MethodType;Ljava/lang/invoke/MethodHandle;Ljava/lang/invoke/MethodType;)Ljava/lang/invoke/CallSite;
   #76 = Methodref          #3.#98        // com/quickly/devploment/single/SingleInstance.lambda$main$0:()V
   #77 = Utf8               run
   #78 = Utf8               ()Ljava/lang/Runnable;
   #79 = Utf8               (Ljava/lang/Runnable;)V
   #80 = Utf8               start
   #81 = Utf8               getPort
   #82 = Utf8               ()Ljava/lang/String;
   #83 = Utf8               java/lang/System
   #84 = Utf8               out
   #85 = Utf8               Ljava/io/PrintStream;
   #86 = Utf8               append
   #87 = Utf8               (Ljava/lang/String;)Ljava/lang/StringBuilder;
   #88 = Utf8               currentThread
   #89 = Utf8               ()Ljava/lang/Thread;
   #90 = Utf8               getName
   #91 = Utf8               (Ljava/lang/Object;)Ljava/lang/StringBuilder;
   #92 = Utf8               toString
   #93 = Utf8               java/io/PrintStream
   #94 = Utf8               println
   #95 = Utf8               (Ljava/lang/String;)V
   #96 = Class              #99           // java/lang/invoke/LambdaMetafactory
   #97 = NameAndType        #100:#104     // metafactory:(Ljava/lang/invoke/MethodHandles$Lookup;Ljava/lang/String;Ljava/lang/invoke/MethodType;Ljava/lang/invoke/MethodType;Ljava/lang/invoke/MethodHandle;Ljava/lang/invoke/MethodType;)Ljava/lang/invoke/CallSite;
   #98 = NameAndType        #39:#29       // lambda$main$0:()V
   #99 = Utf8               java/lang/invoke/LambdaMetafactory
  #100 = Utf8               metafactory
  #101 = Class              #106          // java/lang/invoke/MethodHandles$Lookup
  #102 = Utf8               Lookup
  #103 = Utf8               InnerClasses
  #104 = Utf8               (Ljava/lang/invoke/MethodHandles$Lookup;Ljava/lang/String;Ljava/lang/invoke/MethodType;Ljava/lang/invoke/MethodType;Ljava/lang/invoke/MethodHandle;Ljava/lang/invoke/MethodType;)Ljava/lang/invoke/CallSite;
  #105 = Class              #107          // java/lang/invoke/MethodHandles
  #106 = Utf8               java/lang/invoke/MethodHandles$Lookup
  #107 = Utf8               java/lang/invoke/MethodHandles
{
  public com.quickly.devploment.single.SingleInstance();
    descriptor: ()V
    flags: ACC_PUBLIC
    Code:
      stack=1, locals=1, args_size=1
         0: aload_0
         1: invokespecial #1                  // Method java/lang/Object."<init>":()V
         4: return
      LineNumberTable:
        line 10: 0

  public static com.quickly.devploment.single.SingleObject getSingleObject();
    descriptor: ()Lcom/quickly/devploment/single/SingleObject;
    flags: ACC_PUBLIC, ACC_STATIC
    Code:
      stack=4, locals=2, args_size=0
         0: getstatic     #2                  // Field singleObject:Lcom/quickly/devploment/single/SingleObject;
         3: ifnonnull     41
         6: ldc           #3                  // class com/quickly/devploment/single/SingleInstance
         8: dup
         9: astore_0
        10: monitorenter
        11: getstatic     #2                  // Field singleObject:Lcom/quickly/devploment/single/SingleObject;
        14: ifnonnull     31
        17: new           #4                  // class com/quickly/devploment/single/SingleObject
        20: dup
        21: ldc           #5                  // String name
        23: ldc           #6                  // String port
        25: invokespecial #7                  // Method com/quickly/devploment/single/SingleObject."<init>":(Ljava/lang/String;Ljava/lang/String;)V
        28: putstatic     #2                  // Field singleObject:Lcom/quickly/devploment/single/SingleObject;
        31: aload_0
        32: monitorexit
        33: goto          41
        36: astore_1
        37: aload_0
        38: monitorexit
        39: aload_1
        40: athrow
        41: getstatic     #2                  // Field singleObject:Lcom/quickly/devploment/single/SingleObject;
        44: areturn
      Exception table:
         from    to  target type
            11    33    36   any
            36    39    36   any
      LineNumberTable:
        line 14: 0
        line 15: 6
        line 16: 11
        line 17: 17
        line 19: 31
        line 21: 41
      StackMapTable: number_of_entries = 3
        frame_type = 252 /* append */
          offset_delta = 31
          locals = [ class java/lang/Object ]
        frame_type = 68 /* same_locals_1_stack_item */
          stack = [ class java/lang/Throwable ]
        frame_type = 250 /* chop */
          offset_delta = 4

  public static void main(java.lang.String[]);
    descriptor: ([Ljava/lang/String;)V
    flags: ACC_PUBLIC, ACC_STATIC
    Code:
      stack=3, locals=2, args_size=1
         0: iconst_0
         1: istore_1
         2: iload_1
         3: sipush        1000
         6: if_icmpge     30
         9: new           #8                  // class java/lang/Thread
        12: dup
        13: invokedynamic #9,  0              // InvokeDynamic #0:run:()Ljava/lang/Runnable;
        18: invokespecial #10                 // Method java/lang/Thread."<init>":(Ljava/lang/Runnable;)V
        21: invokevirtual #11                 // Method java/lang/Thread.start:()V
        24: iinc          1, 1
        27: goto          2
        30: return
      LineNumberTable:
        line 26: 0
        line 27: 9
        line 32: 21
        line 26: 24
        line 34: 30
      StackMapTable: number_of_entries = 2
        frame_type = 252 /* append */
          offset_delta = 2
          locals = [ int ]
        frame_type = 250 /* chop */
          offset_delta = 27
}
SourceFile: "SingleInstance.java"
InnerClasses:
     public static final #102= #101 of #105; //Lookup=class java/lang/invoke/MethodHandles$Lookup of class java/lang/invoke/MethodHandles
BootstrapMethods:
  0: #52 invokestatic java/lang/invoke/LambdaMetafactory.metafactory:(Ljava/lang/invoke/MethodHandles$Lookup;Ljava/lang/String;Ljava/lang/invoke/MethodType;Ljava/lang/invoke/MethodType;Ljava/lang/invoke/MethodHandle;Ljava/lang/invoke/MethodType;)Ljava/lang/invoke/CallSite;
    Method arguments:
      #53 ()V
      #54 invokestatic com/quickly/devploment/single/SingleInstance.lambda$main$0:()V
      #53 ()V

E:\gmjavadev\devploment\src\test\java\com\quickly\devploment\single>